bode_testing/__init__.py
bode_testing/_bode_testing.py
bode_testing/requester/__init__.py
bode_testing/requester/_requester.py
bode_testing-0.0.20.dist-info/METADATA
bode_testing-0.0.20.dist-info/WHEEL
bode_testing-0.0.20.dist-info/top_level.txt
bode_testing-0.0.20.dist-info/RECORD
