Metadata-Version: 2.4
Name: bode_testing
Version: 0.0.20
Summary: Testing for for BODE framework
Requires-Dist: pytest
Provides-Extra: requester
Requires-Dist: bode_logger; extra == "requester"
Requires-Dist: requests; extra == "requester"
